{
  "the"    : "\uE000",
  "of"     : "\uE001",
  "to"     : "\uE002",
  "a"      : "\uE003",
  "an"     : "\uF003",
  "in"     : "\uE004",
  "be"     : "\uE005",
  "is"     : "\uF005",
  "are"    : "\uF006",
  "was"    : "\uF007",
  "were"   : "\uF008",
  "it"     : "\uE008",
  "you"    : "\uE009",
  "that"   : "\uE010",
  "he"     : "\uE011",
  "she"    : "\uF011",
  "for"    : "\uE012",
  "on"     : "\uE013",
  "with"   : "\uE014",
  "as"     : "\uE015",
  "I"      : "\uE016",
  "me"     : "\uF016",
  "his"    : "\uE017",
  "her"    : "\uF017",
  "they"   : "\uE018",
  "them"   : "\uF018",
  "at"     : "\uE019",
  "have"   : "\uE020",
  "has"    : "\uF020",
  "this"   : "\uE021",
  "from"   : "\uE022",
  "or"     : "\uE023",
  "by"     : "\uE024",
  "hot"    : "\uE025",
  "word"   : "\uE026",
  "but"    : "\uE027",
  "what"   : "\uE028",
  "some"   : "\uE029",
  "we"     : "\uE030",
  "us"     : "\uF030",
  "can"    : "\uE031",
  "out"    : "\uE032",
  "other"  : "\uE033",
  "all"    : "\uE034",
  "there"  : "\uE035",
  "when"   : "\uE036",
  "up"     : "\uE037",
  "use"    : "\uE038",
  "your"   : "\uE039",
  "say"    : "\uE040",
  "each"   : "\uE041",
  "which"  : "\uE042",
  "do"     : "\uE043",
  "their"  : "\uE044",
  "time"   : "\uE045",
  "if"     : "\uE046",
  "will"   : "\uE047",
  "way"    : "\uE048",
  "about"  : "\uE049",
  "many"   : "\uE050",
  "then"   : "\uE051",
  "write"  : "\uE052",
  "would"  : "\uE053",
  "like"   : "\uE054",
  "so"     : "\uE055",
  "these"  : "\uE056",
  "long"   : "\uE057",
  "make"   : "\uE058",
  "think"  : "\uE059",
  "see"    : "\uE060",
  "loo"    : "\uE061",
  "more"   : "\uE062",
  "day"    : "\uE063",
  "go"     : "\uE064",
  "come"   : "\uE065",
  "number" : "\uE066",
  "sound"  : "\uE067",
  "not"    : "\uE068",
  "most"   : "\uE069",
  "people" : "\uE070",
  "my"     : "\uE071",
  "over"   : "\uE072",
  "know"   : "\uE073",
  "water"  : "\uE074",
  "than"   : "\uE075",
  "call"   : "\uE076",
  "who"    : "\uE077"
}
